[
  {
    "hospitalName": "AADHAR Hospital, Hisar",
    "hospitalAddress": "",
    "normalBedTotal": "",
    "normalBedOccupied": "",
    "normalBedAvailable": "5",
    "oxygenBedTotal": "",
    "oxygenBedOccupied": "26",
    "oxygenBedAvailable": "0",
    "lastUpdatedDate": "9th May,21",
    "lastUpdatedTime": "2:34 PM",
    "district": "Hisar",
    "state": "Haryana",
    "googleSearch": "https://www.google.com/search?q=AADHAR+Hospital, Hisar+Haryana&rlz=1C1CHBF_enIN859IN859&oq=AADHAR+Hospital, Hisar+Haryana&aqs=chrome..69i57j46i10i175i199j0i10l7.11711j0j15&sourceid=chrome&ie=UTF-8",
    "phoneNo": "09729913333"
  },
  {
    "hospitalName": "Bharat Multispeciality Hospital",
    "hospitalAddress": "",
    "normalBedTotal": "",
    "normalBedOccupied": "",
    "normalBedAvailable": "0",
    "oxygenBedTotal": "",
    "oxygenBedOccupied": "24",
    "oxygenBedAvailable": "0",
    "lastUpdatedDate": "9th May,21",
    "lastUpdatedTime": "4:01 PM",
    "district": "Hisar",
    "state": "Haryana",
    "googleSearch": "https://www.google.com/search?q=Bharat+Multispeciality Hospital+Haryana&rlz=1C1CHBF_enIN859IN859&oq=Bharat+Multispeciality Hospital+Haryana&aqs=chrome..69i57j46i10i175i199j0i10l7.11711j0j15&sourceid=chrome&ie=UTF-8",
    "phoneNo": "08862820000"
  },
  {
    "hospitalName": "Central Medical Centre (CMC)",
    "hospitalAddress": "",
    "normalBedTotal": "",
    "normalBedOccupied": "",
    "normalBedAvailable": "0",
    "oxygenBedTotal": "",
    "oxygenBedOccupied": "47",
    "oxygenBedAvailable": "0",
    "lastUpdatedDate": "9th May,21",
    "lastUpdatedTime": "7:40 AM",
    "district": "Hisar",
    "state": "Haryana",
    "googleSearch": "https://www.google.com/search?q=Central+Medical Centre (CMC)+Haryana&rlz=1C1CHBF_enIN859IN859&oq=Central+Medical Centre (CMC)+Haryana&aqs=chrome..69i57j46i10i175i199j0i10l7.11711j0j15&sourceid=chrome&ie=UTF-8",
    "phoneNo": "09996166233"
  },
  {
    "hospitalName": "Ch. Devi Lal Sanjeevani Make Shift Covid Hopsital Hisar",
    "hospitalAddress": "",
    "normalBedTotal": "",
    "normalBedOccupied": "",
    "normalBedAvailable": "129",
    "oxygenBedTotal": "",
    "oxygenBedOccupied": "200",
    "oxygenBedAvailable": "129",
    "lastUpdatedDate": "8th May,21",
    "lastUpdatedTime": "8:35 PM",
    "district": "Hisar",
    "state": "Haryana",
    "googleSearch": "https://www.google.com/search?q=Ch.+Devi Lal Sanjeevani Make Shift Covid Hopsital Hisar+Haryana&rlz=1C1CHBF_enIN859IN859&oq=Ch.+Devi Lal Sanjeevani Make Shift Covid Hopsital Hisar+Haryana&aqs=chrome..69i57j46i10i175i199j0i10l7.11711j0j15&sourceid=chrome&ie=UTF-8",
    "phoneNo": "01662223111"
  },
  {
    "hospitalName": "Churamani Hospital",
    "hospitalAddress": "",
    "normalBedTotal": "",
    "normalBedOccupied": "",
    "normalBedAvailable": "5",
    "oxygenBedTotal": "",
    "oxygenBedOccupied": "5",
    "oxygenBedAvailable": "0",
    "lastUpdatedDate": "9th May,21",
    "lastUpdatedTime": "7:48 AM",
    "district": "Hisar",
    "state": "Haryana",
    "googleSearch": "https://www.google.com/search?q=Churamani+Hospital+Haryana&rlz=1C1CHBF_enIN859IN859&oq=Churamani+Hospital+Haryana&aqs=chrome..69i57j46i10i175i199j0i10l7.11711j0j15&sourceid=chrome&ie=UTF-8",
    "phoneNo": "01162231914"
  },
  {
    "hospitalName": "DR. ANANTRAM JANTA HOSPITAL PVT LTD BARWALA",
    "hospitalAddress": "",
    "normalBedTotal": "",
    "normalBedOccupied": "",
    "normalBedAvailable": "3",
    "oxygenBedTotal": "",
    "oxygenBedOccupied": "17",
    "oxygenBedAvailable": "3",
    "lastUpdatedDate": "9th May,21",
    "lastUpdatedTime": "3:08 PM",
    "district": "Hisar",
    "state": "Haryana",
    "googleSearch": "https://www.google.com/search?q=DR.+ANANTRAM JANTA HOSPITAL PVT LTD BARWALA+Haryana&rlz=1C1CHBF_enIN859IN859&oq=DR.+ANANTRAM JANTA HOSPITAL PVT LTD BARWALA+Haryana&aqs=chrome..69i57j46i10i175i199j0i10l7.11711j0j15&sourceid=chrome&ie=UTF-8",
    "phoneNo": "01693242096"
  },
  {
    "hospitalName": "Geetanjali Hospital",
    "hospitalAddress": "",
    "normalBedTotal": "",
    "normalBedOccupied": "",
    "normalBedAvailable": "3",
    "oxygenBedTotal": "",
    "oxygenBedOccupied": "40",
    "oxygenBedAvailable": "3",
    "lastUpdatedDate": "9th May,21",
    "lastUpdatedTime": "2:43 PM",
    "district": "Hisar",
    "state": "Haryana",
    "googleSearch": "https://www.google.com/search?q=Geetanjali+Hospital+Haryana&rlz=1C1CHBF_enIN859IN859&oq=Geetanjali+Hospital+Haryana&aqs=chrome..69i57j46i10i175i199j0i10l7.11711j0j15&sourceid=chrome&ie=UTF-8",
    "phoneNo": "9812560633"
  },
  {
    "hospitalName": "Goswami Hospital",
    "hospitalAddress": "",
    "normalBedTotal": "",
    "normalBedOccupied": "",
    "normalBedAvailable": "0",
    "oxygenBedTotal": "",
    "oxygenBedOccupied": "4",
    "oxygenBedAvailable": "0",
    "lastUpdatedDate": "9th May,21",
    "lastUpdatedTime": "11:45 AM",
    "district": "Hisar",
    "state": "Haryana",
    "googleSearch": "https://www.google.com/search?q=Goswami+Hospital+Haryana&rlz=1C1CHBF_enIN859IN859&oq=Goswami+Hospital+Haryana&aqs=chrome..69i57j46i10i175i199j0i10l7.11711j0j15&sourceid=chrome&ie=UTF-8",
    "phoneNo": "08929156789"
  },
  {
    "hospitalName": "Gupta Hospital Hisar",
    "hospitalAddress": "",
    "normalBedTotal": "",
    "normalBedOccupied": "",
    "normalBedAvailable": "20",
    "oxygenBedTotal": "",
    "oxygenBedOccupied": "30",
    "oxygenBedAvailable": "20",
    "lastUpdatedDate": "9th May,21",
    "lastUpdatedTime": "12:15 PM",
    "district": "Hisar",
    "state": "Haryana",
    "googleSearch": "https://www.google.com/search?q=Gupta+Hospital Hisar+Haryana&rlz=1C1CHBF_enIN859IN859&oq=Gupta+Hospital Hisar+Haryana&aqs=chrome..69i57j46i10i175i199j0i10l7.11711j0j15&sourceid=chrome&ie=UTF-8",
    "phoneNo": "09254378993"
  },
  {
    "hospitalName": "GURU JAMBHESHWAR MULTISPECIALITY HOSPITAL, AGROHA",
    "hospitalAddress": "",
    "normalBedTotal": "",
    "normalBedOccupied": "",
    "normalBedAvailable": "1",
    "oxygenBedTotal": "",
    "oxygenBedOccupied": "9",
    "oxygenBedAvailable": "0",
    "lastUpdatedDate": "9th May,21",
    "lastUpdatedTime": "10:00 AM",
    "district": "Hisar",
    "state": "Haryana",
    "googleSearch": "https://www.google.com/search?q=GURU+JAMBHESHWAR MULTISPECIALITY HOSPITAL, AGROHA+Haryana&rlz=1C1CHBF_enIN859IN859&oq=GURU+JAMBHESHWAR MULTISPECIALITY HOSPITAL, AGROHA+Haryana&aqs=chrome..69i57j46i10i175i199j0i10l7.11711j0j15&sourceid=chrome&ie=UTF-8",
    "phoneNo": "9812591693"
  },
  {
    "hospitalName": "Holy Help Hospital",
    "hospitalAddress": "",
    "normalBedTotal": "",
    "normalBedOccupied": "",
    "normalBedAvailable": "8",
    "oxygenBedTotal": "",
    "oxygenBedOccupied": "25",
    "oxygenBedAvailable": "1",
    "lastUpdatedDate": "9th May,21",
    "lastUpdatedTime": "12:08 PM",
    "district": "Hisar",
    "state": "Haryana",
    "googleSearch": "https://www.google.com/search?q=Holy+Help Hospital+Haryana&rlz=1C1CHBF_enIN859IN859&oq=Holy+Help Hospital+Haryana&aqs=chrome..69i57j46i10i175i199j0i10l7.11711j0j15&sourceid=chrome&ie=UTF-8",
    "phoneNo": "0162247727"
  },
  {
    "hospitalName": "Janki Children Hospital Hisar",
    "hospitalAddress": "",
    "normalBedTotal": "",
    "normalBedOccupied": "",
    "normalBedAvailable": "2",
    "oxygenBedTotal": "",
    "oxygenBedOccupied": "0",
    "oxygenBedAvailable": "0",
    "lastUpdatedDate": "9th May,21",
    "lastUpdatedTime": "12:50 PM",
    "district": "Hisar",
    "state": "Haryana",
    "googleSearch": "https://www.google.com/search?q=Janki+Children Hospital Hisar+Haryana&rlz=1C1CHBF_enIN859IN859&oq=Janki+Children Hospital Hisar+Haryana&aqs=chrome..69i57j46i10i175i199j0i10l7.11711j0j15&sourceid=chrome&ie=UTF-8",
    "phoneNo": "9991953157"
  },
  {
    "hospitalName": "Mahatma Gandhi Hospital",
    "hospitalAddress": "",
    "normalBedTotal": "",
    "normalBedOccupied": "",
    "normalBedAvailable": "10",
    "oxygenBedTotal": "",
    "oxygenBedOccupied": "19",
    "oxygenBedAvailable": "0",
    "lastUpdatedDate": "9th May,21",
    "lastUpdatedTime": "7:47 AM",
    "district": "Hisar",
    "state": "Haryana",
    "googleSearch": "https://www.google.com/search?q=Mahatma+Gandhi Hospital+Haryana&rlz=1C1CHBF_enIN859IN859&oq=Mahatma+Gandhi Hospital+Haryana&aqs=chrome..69i57j46i10i175i199j0i10l7.11711j0j15&sourceid=chrome&ie=UTF-8",
    "phoneNo": "01662247111"
  },
  {
    "hospitalName": "MAMC Agroha",
    "hospitalAddress": "",
    "normalBedTotal": "",
    "normalBedOccupied": "",
    "normalBedAvailable": "0",
    "oxygenBedTotal": "",
    "oxygenBedOccupied": "85",
    "oxygenBedAvailable": "0",
    "lastUpdatedDate": "9th May,21",
    "lastUpdatedTime": "7:40 AM",
    "district": "Hisar",
    "state": "Haryana",
    "googleSearch": "https://www.google.com/search?q=MAMC+Agroha+Haryana&rlz=1C1CHBF_enIN859IN859&oq=MAMC+Agroha+Haryana&aqs=chrome..69i57j46i10i175i199j0i10l7.11711j0j15&sourceid=chrome&ie=UTF-8",
    "phoneNo": "01669281193"
  },
  {
    "hospitalName": "Medi City Hospital",
    "hospitalAddress": "",
    "normalBedTotal": "",
    "normalBedOccupied": "",
    "normalBedAvailable": "13",
    "oxygenBedTotal": "",
    "oxygenBedOccupied": "13",
    "oxygenBedAvailable": "13",
    "lastUpdatedDate": "9th May,21",
    "lastUpdatedTime": "7:44 AM",
    "district": "Hisar",
    "state": "Haryana",
    "googleSearch": "https://www.google.com/search?q=Medi+City Hospital+Haryana&rlz=1C1CHBF_enIN859IN859&oq=Medi+City Hospital+Haryana&aqs=chrome..69i57j46i10i175i199j0i10l7.11711j0j15&sourceid=chrome&ie=UTF-8",
    "phoneNo": "9416044519"
  },
  {
    "hospitalName": "Military Hospital Hisar",
    "hospitalAddress": "",
    "normalBedTotal": "",
    "normalBedOccupied": "",
    "normalBedAvailable": "0",
    "oxygenBedTotal": "",
    "oxygenBedOccupied": "16",
    "oxygenBedAvailable": "0",
    "lastUpdatedDate": "9th May,21",
    "lastUpdatedTime": "7:47 AM",
    "district": "Hisar",
    "state": "Haryana",
    "googleSearch": "https://www.google.com/search?q=Military+Hospital Hisar+Haryana&rlz=1C1CHBF_enIN859IN859&oq=Military+Hospital Hisar+Haryana&aqs=chrome..69i57j46i10i175i199j0i10l7.11711j0j15&sourceid=chrome&ie=UTF-8",
    "phoneNo": "09896768373"
  },
  {
    "hospitalName": "Noble Super Specialty Hospital",
    "hospitalAddress": "",
    "normalBedTotal": "",
    "normalBedOccupied": "",
    "normalBedAvailable": "7",
    "oxygenBedTotal": "",
    "oxygenBedOccupied": "12",
    "oxygenBedAvailable": "7",
    "lastUpdatedDate": "9th May,21",
    "lastUpdatedTime": "12:02 PM",
    "district": "Hisar",
    "state": "Haryana",
    "googleSearch": "https://www.google.com/search?q=Noble+Super Specialty Hospital+Haryana&rlz=1C1CHBF_enIN859IN859&oq=Noble+Super Specialty Hospital+Haryana&aqs=chrome..69i57j46i10i175i199j0i10l7.11711j0j15&sourceid=chrome&ie=UTF-8",
    "phoneNo": "09315655000"
  },
  {
    "hospitalName": "OPJindal Institute of Cancer & Research Hospital",
    "hospitalAddress": "",
    "normalBedTotal": "",
    "normalBedOccupied": "",
    "normalBedAvailable": "4",
    "oxygenBedTotal": "",
    "oxygenBedOccupied": "102",
    "oxygenBedAvailable": "0",
    "lastUpdatedDate": "9th May,21",
    "lastUpdatedTime": "7:50 AM",
    "district": "Hisar",
    "state": "Haryana",
    "googleSearch": "https://www.google.com/search?q=OPJindal+Institute of Cancer & Research Hospital+Haryana&rlz=1C1CHBF_enIN859IN859&oq=OPJindal+Institute of Cancer & Research Hospital+Haryana&aqs=chrome..69i57j46i10i175i199j0i10l7.11711j0j15&sourceid=chrome&ie=UTF-8",
    "phoneNo": "01662221169"
  },
  {
    "hospitalName": "PARDEEP KANSAL MULTISPECIALITY HOSPITAL FOR CHILDREN",
    "hospitalAddress": "",
    "normalBedTotal": "",
    "normalBedOccupied": "",
    "normalBedAvailable": "12",
    "oxygenBedTotal": "",
    "oxygenBedOccupied": "0",
    "oxygenBedAvailable": "0",
    "lastUpdatedDate": "9th May,21",
    "lastUpdatedTime": "7:49 AM",
    "district": "Hisar",
    "state": "Haryana",
    "googleSearch": "https://www.google.com/search?q=PARDEEP+KANSAL MULTISPECIALITY HOSPITAL FOR CHILDREN+Haryana&rlz=1C1CHBF_enIN859IN859&oq=PARDEEP+KANSAL MULTISPECIALITY HOSPITAL FOR CHILDREN+Haryana&aqs=chrome..69i57j46i10i175i199j0i10l7.11711j0j15&sourceid=chrome&ie=UTF-8",
    "phoneNo": "8168093957"
  },
  {
    "hospitalName": "Parnami Hospital",
    "hospitalAddress": "",
    "normalBedTotal": "",
    "normalBedOccupied": "",
    "normalBedAvailable": "10",
    "oxygenBedTotal": "",
    "oxygenBedOccupied": "21",
    "oxygenBedAvailable": "5",
    "lastUpdatedDate": "9th May,21",
    "lastUpdatedTime": "2:33 PM",
    "district": "Hisar",
    "state": "Haryana",
    "googleSearch": "https://www.google.com/search?q=Parnami+Hospital+Haryana&rlz=1C1CHBF_enIN859IN859&oq=Parnami+Hospital+Haryana&aqs=chrome..69i57j46i10i175i199j0i10l7.11711j0j15&sourceid=chrome&ie=UTF-8",
    "phoneNo": "9654210700"
  },
  {
    "hospitalName": "Ravindra Hospital Hisar",
    "hospitalAddress": "",
    "normalBedTotal": "",
    "normalBedOccupied": "",
    "normalBedAvailable": "4",
    "oxygenBedTotal": "",
    "oxygenBedOccupied": "19",
    "oxygenBedAvailable": "4",
    "lastUpdatedDate": "9th May,21",
    "lastUpdatedTime": "7:46 AM",
    "district": "Hisar",
    "state": "Haryana",
    "googleSearch": "https://www.google.com/search?q=Ravindra+Hospital Hisar+Haryana&rlz=1C1CHBF_enIN859IN859&oq=Ravindra+Hospital Hisar+Haryana&aqs=chrome..69i57j46i10i175i199j0i10l7.11711j0j15&sourceid=chrome&ie=UTF-8",
    "phoneNo": "01662223120"
  },
  {
    "hospitalName": "Sapra Hospital",
    "hospitalAddress": "",
    "normalBedTotal": "",
    "normalBedOccupied": "",
    "normalBedAvailable": "18",
    "oxygenBedTotal": "",
    "oxygenBedOccupied": "35",
    "oxygenBedAvailable": "14",
    "lastUpdatedDate": "9th May,21",
    "lastUpdatedTime": "11:48 AM",
    "district": "Hisar",
    "state": "Haryana",
    "googleSearch": "https://www.google.com/search?q=Sapra+Hospital+Haryana&rlz=1C1CHBF_enIN859IN859&oq=Sapra+Hospital+Haryana&aqs=chrome..69i57j46i10i175i199j0i10l7.11711j0j15&sourceid=chrome&ie=UTF-8",
    "phoneNo": "09896015883"
  },
  {
    "hospitalName": "Sarvodya Hospital, Hisar",
    "hospitalAddress": "",
    "normalBedTotal": "",
    "normalBedOccupied": "",
    "normalBedAvailable": "0",
    "oxygenBedTotal": "",
    "oxygenBedOccupied": "24",
    "oxygenBedAvailable": "0",
    "lastUpdatedDate": "9th May,21",
    "lastUpdatedTime": "10:53 AM",
    "district": "Hisar",
    "state": "Haryana",
    "googleSearch": "https://www.google.com/search?q=Sarvodya+Hospital, Hisar+Haryana&rlz=1C1CHBF_enIN859IN859&oq=Sarvodya+Hospital, Hisar+Haryana&aqs=chrome..69i57j46i10i175i199j0i10l7.11711j0j15&sourceid=chrome&ie=UTF-8",
    "phoneNo": "8059969960"
  },
  {
    "hospitalName": "Sewak Sabha Hospital",
    "hospitalAddress": "",
    "normalBedTotal": "",
    "normalBedOccupied": "",
    "normalBedAvailable": "2",
    "oxygenBedTotal": "",
    "oxygenBedOccupied": "16",
    "oxygenBedAvailable": "0",
    "lastUpdatedDate": "9th May,21",
    "lastUpdatedTime": "11:43 AM",
    "district": "Hisar",
    "state": "Haryana",
    "googleSearch": "https://www.google.com/search?q=Sewak+Sabha Hospital+Haryana&rlz=1C1CHBF_enIN859IN859&oq=Sewak+Sabha Hospital+Haryana&aqs=chrome..69i57j46i10i175i199j0i10l7.11711j0j15&sourceid=chrome&ie=UTF-8",
    "phoneNo": "9812742254"
  },
  {
    "hospitalName": "Shanti Devi Hospital",
    "hospitalAddress": "",
    "normalBedTotal": "",
    "normalBedOccupied": "",
    "normalBedAvailable": "2",
    "oxygenBedTotal": "",
    "oxygenBedOccupied": "26",
    "oxygenBedAvailable": "2",
    "lastUpdatedDate": "9th May,21",
    "lastUpdatedTime": "7:44 AM",
    "district": "Hisar",
    "state": "Haryana",
    "googleSearch": "https://www.google.com/search?q=Shanti+Devi Hospital+Haryana&rlz=1C1CHBF_enIN859IN859&oq=Shanti+Devi Hospital+Haryana&aqs=chrome..69i57j46i10i175i199j0i10l7.11711j0j15&sourceid=chrome&ie=UTF-8",
    "phoneNo": "09034013081"
  },
  {
    "hospitalName": "Shri Kali Devi Hospital Hansi",
    "hospitalAddress": "",
    "normalBedTotal": "",
    "normalBedOccupied": "",
    "normalBedAvailable": "13",
    "oxygenBedTotal": "",
    "oxygenBedOccupied": "8",
    "oxygenBedAvailable": "8",
    "lastUpdatedDate": "9th May,21",
    "lastUpdatedTime": "7:43 AM",
    "district": "Hisar",
    "state": "Haryana",
    "googleSearch": "https://www.google.com/search?q=Shri+Kali Devi Hospital Hansi+Haryana&rlz=1C1CHBF_enIN859IN859&oq=Shri+Kali Devi Hospital Hansi+Haryana&aqs=chrome..69i57j46i10i175i199j0i10l7.11711j0j15&sourceid=chrome&ie=UTF-8",
    "phoneNo": "01663259870"
  },
  {
    "hospitalName": "SINGLA MULTISPECIALITY HOSPITAL",
    "hospitalAddress": "",
    "normalBedTotal": "",
    "normalBedOccupied": "",
    "normalBedAvailable": "0",
    "oxygenBedTotal": "",
    "oxygenBedOccupied": "17",
    "oxygenBedAvailable": "0",
    "lastUpdatedDate": "9th May,21",
    "lastUpdatedTime": "2:12 PM",
    "district": "Hisar",
    "state": "Haryana",
    "googleSearch": "https://www.google.com/search?q=SINGLA+MULTISPECIALITY HOSPITAL+Haryana&rlz=1C1CHBF_enIN859IN859&oq=SINGLA+MULTISPECIALITY HOSPITAL+Haryana&aqs=chrome..69i57j46i10i175i199j0i10l7.11711j0j15&sourceid=chrome&ie=UTF-8",
    "phoneNo": "09996357571"
  },
  {
    "hospitalName": "SL Minda Hospital",
    "hospitalAddress": "",
    "normalBedTotal": "",
    "normalBedOccupied": "",
    "normalBedAvailable": "4",
    "oxygenBedTotal": "",
    "oxygenBedOccupied": "6",
    "oxygenBedAvailable": "2",
    "lastUpdatedDate": "9th May,21",
    "lastUpdatedTime": "10:31 AM",
    "district": "Hisar",
    "state": "Haryana",
    "googleSearch": "https://www.google.com/search?q=SL+Minda Hospital+Haryana&rlz=1C1CHBF_enIN859IN859&oq=SL+Minda Hospital+Haryana&aqs=chrome..69i57j46i10i175i199j0i10l7.11711j0j15&sourceid=chrome&ie=UTF-8",
    "phoneNo": "7082984604"
  },
  {
    "hospitalName": "Sonakshi Children Hospital Hansi",
    "hospitalAddress": "",
    "normalBedTotal": "",
    "normalBedOccupied": "",
    "normalBedAvailable": "3",
    "oxygenBedTotal": "",
    "oxygenBedOccupied": "9",
    "oxygenBedAvailable": "3",
    "lastUpdatedDate": "9th May,21",
    "lastUpdatedTime": "11:04 AM",
    "district": "Hisar",
    "state": "Haryana",
    "googleSearch": "https://www.google.com/search?q=Sonakshi+Children Hospital Hansi+Haryana&rlz=1C1CHBF_enIN859IN859&oq=Sonakshi+Children Hospital Hansi+Haryana&aqs=chrome..69i57j46i10i175i199j0i10l7.11711j0j15&sourceid=chrome&ie=UTF-8",
    "phoneNo": "8168024495"
  },
  {
    "hospitalName": "Sukhda Multispeciality Hospital",
    "hospitalAddress": "",
    "normalBedTotal": "",
    "normalBedOccupied": "",
    "normalBedAvailable": "7",
    "oxygenBedTotal": "",
    "oxygenBedOccupied": "46",
    "oxygenBedAvailable": "3",
    "lastUpdatedDate": "9th May,21",
    "lastUpdatedTime": "10:53 AM",
    "district": "Hisar",
    "state": "Haryana",
    "googleSearch": "https://www.google.com/search?q=Sukhda+Multispeciality Hospital+Haryana&rlz=1C1CHBF_enIN859IN859&oq=Sukhda+Multispeciality Hospital+Haryana&aqs=chrome..69i57j46i10i175i199j0i10l7.11711j0j15&sourceid=chrome&ie=UTF-8",
    "phoneNo": "09996544005"
  },
  {
    "hospitalName": "Vardaan Hospital Hisar",
    "hospitalAddress": "",
    "normalBedTotal": "",
    "normalBedOccupied": "",
    "normalBedAvailable": "7",
    "oxygenBedTotal": "",
    "oxygenBedOccupied": "9",
    "oxygenBedAvailable": "4",
    "lastUpdatedDate": "9th May,21",
    "lastUpdatedTime": "1:26 PM",
    "district": "Hisar",
    "state": "Haryana",
    "googleSearch": "https://www.google.com/search?q=Vardaan+Hospital Hisar+Haryana&rlz=1C1CHBF_enIN859IN859&oq=Vardaan+Hospital Hisar+Haryana&aqs=chrome..69i57j46i10i175i199j0i10l7.11711j0j15&sourceid=chrome&ie=UTF-8",
    "phoneNo": "7947415301"
  }
]